msg91_sms/__init__.py
msg91_sms-1.0.2.dist-info/LICENSE
msg91_sms-1.0.2.dist-info/METADATA
msg91_sms-1.0.2.dist-info/WHEEL
msg91_sms-1.0.2.dist-info/top_level.txt
msg91_sms-1.0.2.dist-info/RECORD
