Metadata-Version: 2.1
Name: msg91-sms
Version: 1.0.2
Summary: A simple and easy to use Python package to send SMS using MSG91 SMS API.
Home-page: https://www.codespeedy.com/
Author: CodeSpeedy Technology Pvt. Ltd.
License: MIT
Keywords: msg91-sms msg91 sms
Platform: UNKNOWN
Requires-Python: >=3.2
Requires-Dist: requests
Requires-Dist: json
